pytest_nbsmoke.py
pytest_nbsmoke-0.1.6.dist-info/DESCRIPTION.rst
pytest_nbsmoke-0.1.6.dist-info/METADATA
pytest_nbsmoke-0.1.6.dist-info/RECORD
pytest_nbsmoke-0.1.6.dist-info/WHEEL
pytest_nbsmoke-0.1.6.dist-info/entry_points.txt
pytest_nbsmoke-0.1.6.dist-info/metadata.json
pytest_nbsmoke-0.1.6.dist-info/top_level.txt
