Metadata-Version: 2.0
Name: pytest-nbsmoke
Version: 0.1.6
Summary: Basic notebook checks. Do they run? Do they contain lint?
Home-page: https://github.com/ContinuumIO/nbsmoke
Author: pytest-nbsmoke contributors
Author-email: UNKNOWN
License: BSD-3
Platform: UNKNOWN
Classifier: Development Status :: 3 - Alpha
Classifier: Framework :: Pytest
Classifier: Intended Audience :: Developers
Classifier: Topic :: Software Development :: Testing
Classifier: Programming Language :: Python
Classifier: Programming Language :: Python :: 2
Classifier: Programming Language :: Python :: 3
Classifier: Programming Language :: Python :: Implementation :: CPython
Classifier: Programming Language :: Python :: Implementation :: PyPy
Classifier: Operating System :: OS Independent
Classifier: License :: OSI Approved :: BSD License
Requires-Dist: pytest (>=3.1.1)
Requires-Dist: jupyter-client
Requires-Dist: ipykernel
Requires-Dist: nbformat
Requires-Dist: nbconvert
Requires-Dist: pyflakes
